rory/__init__.py
rory/controller_manager.py
rory/interactor.py
rory/interface.py
rory/midiinterface.py
rory/player.py
rory/structures.py
rory-0.3.9.dist-info/LICENSE
rory-0.3.9.dist-info/METADATA
rory-0.3.9.dist-info/WHEEL
rory-0.3.9.dist-info/entry_points.txt
rory-0.3.9.dist-info/top_level.txt
rory-0.3.9.dist-info/RECORD
