Metadata-Version: 2.1
Name: rory
Version: 0.3.9
Summary: Play along to MIDI files in console
Home-page: https://burnsomni.net/git/rory
Author: Quintin Smith
Author-email: smith.quintin@protonmail.com
License: GPL-2.0
Classifier: Programming Language :: Python :: 3
Classifier: License :: OSI Approved :: GNU General Public License v2 (GPLv2)
Classifier: Operating System :: POSIX :: Linux
Requires-Python: ~=3.7
License-File: LICENSE
Requires-Dist: asyncinotify
Requires-Dist: wrecked
Requires-Dist: apres
